dynabayes/__init__.py
dynabayes/inference.py
dynabayes/model.py
dynabayes/simulate.py
dynabayes/utils.py
dynabayes/visualize.py
dynabayes-0.1.0.dist-info/METADATA
dynabayes-0.1.0.dist-info/WHEEL
dynabayes-0.1.0.dist-info/top_level.txt
dynabayes-0.1.0.dist-info/RECORD
