Metadata-Version: 2.2
Name: dynabayes
Version: 0.1.0
Summary: Dynamic Bayesian Inference Package
Home-page: https://github.com/p3dr0id/DynaBayes
Author: Pedro D. Pinto
Author-email: pedrodp42@gmail.com
Classifier: Programming Language :: Python :: 3
Classifier: License :: OSI Approved :: MIT License
Classifier: Operating System :: OS Independent
Requires-Python: >=3.8
Requires-Dist: numpy
Requires-Dist: matplotlib
Requires-Dist: pandas
Dynamic: author
Dynamic: author-email
Dynamic: classifier
Dynamic: description
Dynamic: description-content-type
Dynamic: home-page
Dynamic: requires-dist
Dynamic: requires-python
Dynamic: summary
